elib/__init__.py
elib/bitcoincashElectrum/__init__.py
elib/bitcoincashElectrum/address.py
elib/bitcoincashElectrum/asert_daa.py
elib/bitcoincashElectrum/base_wizard.py
elib/bitcoincashElectrum/bip32.py
elib/bitcoincashElectrum/bitcoin.py
elib/bitcoincashElectrum/blockchain.py
elib/bitcoincashElectrum/caches.py
elib/bitcoincashElectrum/cashacct.py
elib/bitcoincashElectrum/cashaddr.py
elib/bitcoincashElectrum/coinchooser.py
elib/bitcoincashElectrum/commands.py
elib/bitcoincashElectrum/contacts.py
elib/bitcoincashElectrum/daemon.py
elib/bitcoincashElectrum/dnssec.py
elib/bitcoincashElectrum/ecc.py
elib/bitcoincashElectrum/ecc_fast.py
elib/bitcoincashElectrum/ecc_fast2.py
elib/bitcoincashElectrum/exchange_rate.py
elib/bitcoincashElectrum/i18n.py
elib/bitcoincashElectrum/interface.py
elib/bitcoincashElectrum/jsonrpc.py
elib/bitcoincashElectrum/keystore.py
elib/bitcoincashElectrum/mnemonic.py
elib/bitcoincashElectrum/msqr.py
elib/bitcoincashElectrum/network.py
elib/bitcoincashElectrum/networks.py
elib/bitcoincashElectrum/old_contacts.py
elib/bitcoincashElectrum/old_mnemonic.py
elib/bitcoincashElectrum/paymentrequest.py
elib/bitcoincashElectrum/paymentrequest_pb2.py
elib/bitcoincashElectrum/pem.py
elib/bitcoincashElectrum/plot.py
elib/bitcoincashElectrum/plugin.py
elib/bitcoincashElectrum/ripemd.py
elib/bitcoincashElectrum/rsakey.py
elib/bitcoincashElectrum/schnorr.py
elib/bitcoincashElectrum/secp256k1.py
elib/bitcoincashElectrum/serialize.py
elib/bitcoincashElectrum/simple_config.py
elib/bitcoincashElectrum/storage.py
elib/bitcoincashElectrum/synchronizer.py
elib/bitcoincashElectrum/token.py
elib/bitcoincashElectrum/token_meta.py
elib/bitcoincashElectrum/transaction.py
elib/bitcoincashElectrum/util.py
elib/bitcoincashElectrum/verifier.py
elib/bitcoincashElectrum/version.py
elib/bitcoincashElectrum/wallet.py
elib/bitcoincashElectrum/web.py
elib/bitcoincashElectrum/websockets.py
elib/bitcoincashElectrum/winconsole.py
elib/bitcoincashElectrum/x509.py
electrum_bch-0.3.9.dist-info/METADATA
electrum_bch-0.3.9.dist-info/WHEEL
electrum_bch-0.3.9.dist-info/top_level.txt
electrum_bch-0.3.9.dist-info/RECORD
